.gitignore
CHANGES.txt
CONTRIBUTORS.txt
MANIFEST.in
README.txt
setup.py
docs/LICENSE.GPL
docs/LICENSE.txt
src/raptus/__init__.py
src/raptus.article.parallax.egg-info/PKG-INFO
src/raptus.article.parallax.egg-info/SOURCES.txt
src/raptus.article.parallax.egg-info/dependency_links.txt
src/raptus.article.parallax.egg-info/entry_points.txt
src/raptus.article.parallax.egg-info/namespace_packages.txt
src/raptus.article.parallax.egg-info/not-zip-safe
src/raptus.article.parallax.egg-info/requires.txt
src/raptus.article.parallax.egg-info/top_level.txt
src/raptus/article/__init__.py
src/raptus/article/parallax/__init__.py
src/raptus/article/parallax/configure.zcml
src/raptus/article/parallax/browser/__init__.py
src/raptus/article/parallax/browser/configure.zcml
src/raptus/article/parallax/browser/parallax.pt
src/raptus/article/parallax/browser/parallax.py
src/raptus/article/parallax/browser/static/parallax.css
src/raptus/article/parallax/browser/static/parallax.js
src/raptus/article/parallax/locales/raptus.article.parallax.pot
src/raptus/article/parallax/locales/de/LC_MESSAGES/raptus.article.parallax.mo
src/raptus/article/parallax/locales/de/LC_MESSAGES/raptus.article.parallax.po
src/raptus/article/parallax/locales/fr/LC_MESSAGES/raptus.article.parallax.mo
src/raptus/article/parallax/locales/fr/LC_MESSAGES/raptus.article.parallax.po
src/raptus/article/parallax/profiles/default/cssregistry.xml
src/raptus/article/parallax/profiles/default/jsregistry.xml
src/raptus/article/parallax/profiles/default/metadata.xml
src/raptus/article/parallax/profiles/default/propertiestool.xml
src/raptus/article/parallax/profiles/default/viewlets.xml