Metadata-Version: 1.0
Name: raptus.article.parallax
Version: 1.0a3
Summary: Parallax effect for raptus articles
Home-page: https://github.com/Raptus/raptus.article.parallax
Author: Raptus AG
Author-email: dev@raptus.com
License: gpl
Platform: UNKNOWN
Classifier: Programming Language :: Python
